voxyl/__init__.py
voxyl/client.py
voxyl/constants.py
voxyl/errors.py
voxyl/models/__init__.py
voxyl/models/achievements.py
voxyl/models/guild.py
voxyl/models/leaderboard.py
voxyl/models/player.py
voxyl/models/utils.py
voxyl/models/games/__init__.py
voxyl/models/games/bed_rush.py
voxyl/models/games/bedwalls.py
voxyl/models/games/bedwars_late.py
voxyl/models/games/bedwars_mega.py
voxyl/models/games/bedwars_normal.py
voxyl/models/games/bedwars_rush.py
voxyl/models/games/bow_fight.py
voxyl/models/games/bridge_fight.py
voxyl/models/games/default_game_structure.py
voxyl/models/games/flat_fight.py
voxyl/models/games/four_way_bridges.py
voxyl/models/games/ground_fight.py
voxyl/models/games/ladder_fight.py
voxyl/models/games/mini_wars.py
voxyl/models/games/obstacles.py
voxyl/models/games/party_games.py
voxyl/models/games/pearl_fight.py
voxyl/models/games/ranked_fours_practice.py
voxyl/models/games/resource_collect.py
voxyl/models/games/resource_old_collect.py
voxyl/models/games/stick_fight.py
voxyl/models/games/sumo.py
voxyl/models/games/sumo_duels.py
voxyl/models/games/void_fight.py
voxylstats-1.5.0.dist-info/LICENSE
voxylstats-1.5.0.dist-info/METADATA
voxylstats-1.5.0.dist-info/WHEEL
voxylstats-1.5.0.dist-info/top_level.txt
voxylstats-1.5.0.dist-info/RECORD
