Metadata-Version: 2.1
Name: voxylstats
Version: 1.5.0
Summary: A simple python wrapper for the Voxyl API
Author: _lightninq & firestarad
License: MIT
License-File: LICENSE
